{
	"credit": "Made by Poloskun_ http://www.youtube.com/c/Enchig",
	"textures": {
		"0": "custom/items/food/salmon_bank",
		"particle": "custom/items/food/salmon_bank"
	},
	"elements": [
		{
			"from": [0, 0, 0],
			"to": [16, 8, 16],
			"faces": {
				"north": {"uv": [8, 12, 16, 16], "texture": "#0"},
				"east": {"uv": [0, 12, 8, 16], "texture": "#0"},
				"south": {"uv": [8, 12, 16, 16], "texture": "#0"},
				"west": {"uv": [8, 12, 16, 16], "texture": "#0"},
				"up": {"uv": [16, 4, 8, 12], "rotation": 90, "texture": "#0"},
				"down": {"uv": [0, 4, 8, 12], "texture": "#0"}
			}
		},
		{
			"from": [2.32, 13.65, 0],
			"to": [18.32, 13.65, 16],
			"rotation": {"angle": 45, "axis": "z", "origin": [8, 8, 8]},
			"faces": {
				"north": {"uv": [8, 12, 16, 16], "texture": "#missing"},
				"east": {"uv": [0, 12, 8, 16], "texture": "#missing"},
				"south": {"uv": [8, 12, 16, 16], "texture": "#missing"},
				"west": {"uv": [8, 12, 16, 16], "texture": "#missing"},
				"up": {"uv": [0, 4, 8, 12], "rotation": 180, "texture": "#0"},
				"down": {"uv": [0, 4, 8, 12], "rotation": 90, "texture": "#0"}
			}
		},
		{
			"from": [6.4, 17.17, 5],
			"to": [15.4, 17.17, 11],
			"rotation": {"angle": 22.5, "axis": "z", "origin": [8, 8, 8]},
			"faces": {
				"north": {"uv": [8, 12, 16, 16], "texture": "#missing"},
				"east": {"uv": [0, 12, 8, 16], "texture": "#missing"},
				"south": {"uv": [8, 12, 16, 16], "texture": "#missing"},
				"west": {"uv": [8, 12, 16, 16], "texture": "#missing"},
				"up": {"uv": [0, 0, 3, 4], "rotation": 90, "texture": "#0"},
				"down": {"uv": [0, 0, 3, 4], "rotation": 90, "texture": "#0"}
			}
		}
	],
	"display": {
		"thirdperson_righthand": {
			"rotation": [47, 35, 0],
			"translation": [0, 1.75, 0],
			"scale": [0.34, 0.34, 0.34]
		},
		"thirdperson_lefthand": {
			"rotation": [47, 35, 0],
			"translation": [0, 1.75, 0],
			"scale": [0.34, 0.34, 0.34]
		},
		"firstperson_righthand": {
			"rotation": [-19, -162, 0],
			"translation": [2.5, 2, 0],
			"scale": [0.25, 0.25, 0.25]
		},
		"firstperson_lefthand": {
			"rotation": [-19, 20, 0],
			"translation": [2.5, 2, 0],
			"scale": [0.25, 0.25, 0.25]
		},
		"ground": {
			"translation": [0, 1.5, 0],
			"scale": [0.25, 0.25, 0.25]
		},
		"gui": {
			"rotation": [35, -136, 0],
			"translation": [0, 0.5, 0],
			"scale": [0.58, 0.58, 0.58]
		},
		"head": {
			"rotation": [0, 56, 0],
			"translation": [0, 11.35, 0],
			"scale": [0.62, 0.62, 0.62]
		},
		"fixed": {
			"rotation": [-90, 0, 0],
			"translation": [0, 0, -6],
			"scale": [0.77, 0.77, 0.77]
		}
	}
}