{
    "parent":    "item/generated",
    "textures":  {
        "layer0": "item/leather_horse_armor"
    },
    "overrides": [
        { "predicate": { "custom_model_data": 1  }, "model": "whomine:rename/3d_glasses" },
        { "predicate": { "custom_model_data": 2  }, "model": "whomine:rename/bee" },
        { "predicate": { "custom_model_data": 3  }, "model": "whomine:rename/bee_nectar" },
        { "predicate": { "custom_model_data": 4  }, "model": "whomine:rename/bee_angry" },
        { "predicate": { "custom_model_data": 5  }, "model": "whomine:rename/bee_angry_nectar" },
        { "predicate": { "custom_model_data": 6  }, "model": "whomine:rename/phantom" },
        { "predicate": { "custom_model_data": 7  }, "model": "whomine:rename/beret" },
        { "predicate": { "custom_model_data": 8  }, "model": "whomine:rename/cap" },
        { "predicate": { "custom_model_data": 9  }, "model": "whomine:rename/cardboard_crown" },
        { "predicate": { "custom_model_data": 10 }, "model": "whomine:rename/chef_hat" },
        { "predicate": { "custom_model_data": 11 }, "model": "whomine:rename/povar_hat" },
        { "predicate": { "custom_model_data": 12 }, "model": "whomine:rename/enchanter_hat" },
        { "predicate": { "custom_model_data": 13 }, "model": "whomine:rename/goat_head" },
        { "predicate": { "custom_model_data": 14 }, "model": "whomine:rename/medicine_mask" },
        { "predicate": { "custom_model_data": 15 }, "model": "whomine:rename/neanderthal_mask" },
        { "predicate": { "custom_model_data": 16 }, "model": "whomine:rename/neanderthal_mask_gaping" },
        { "predicate": { "custom_model_data": 17 }, "model": "whomine:rename/neanderthal_mask_leaves" },
        { "predicate": { "custom_model_data": 18 }, "model": "whomine:rename/neanderthal_mask_leaves_gaping" },
        { "predicate": { "custom_model_data": 19 }, "model": "whomine:rename/golden_eye_prothesis_left" },
        { "predicate": { "custom_model_data": 20 }, "model": "whomine:rename/golden_eye_prothesis_right" },
        { "predicate": { "custom_model_data": 21 }, "model": "whomine:rename/silver_eye_prothesis_left" },
        { "predicate": { "custom_model_data": 22 }, "model": "whomine:rename/silver_eye_prothesis_right" },
        { "predicate": { "custom_model_data": 23 }, "model": "whomine:rename/raccoon_hat" },
        { "predicate": { "custom_model_data": 24 }, "model": "whomine:rename/kabuto" },
        { "predicate": { "custom_model_data": 25 }, "model": "whomine:rename/kabuto_somen" },
        { "predicate": { "custom_model_data": 26 }, "model": "whomine:rename/sculk" },
        { "predicate": { "custom_model_data": 27 }, "model": "whomine:rename/sun_hat" },
        { "predicate": { "custom_model_data": 28 }, "model": "whomine:rename/waiter_cap" },
        { "predicate": { "custom_model_data": 29 }, "model": "whomine:rename/western_hat" },
        { "predicate": { "custom_model_data": 30 }, "model": "whomine:rename/wolf_head" },
        { "predicate": { "custom_model_data": 31 }, "model": "whomine:rename/armorer_hat" },
        { "predicate": { "custom_model_data": 32 }, "model": "whomine:rename/butcher_hat" },
        { "predicate": { "custom_model_data": 33 }, "model": "whomine:rename/cartographer_hat" },
        { "predicate": { "custom_model_data": 34 }, "model": "whomine:rename/desert_hat" },
        { "predicate": { "custom_model_data": 35 }, "model": "whomine:rename/farmer_hat" },
        { "predicate": { "custom_model_data": 36 }, "model": "whomine:rename/fisherman_hat" },
        { "predicate": { "custom_model_data": 37 }, "model": "whomine:rename/fletcher_hat" },
        { "predicate": { "custom_model_data": 38 }, "model": "whomine:rename/librarian_hat" },
        { "predicate": { "custom_model_data": 39 }, "model": "whomine:rename/savanna_hat" },
        { "predicate": { "custom_model_data": 40 }, "model": "whomine:rename/shepherd_hat" },
        { "predicate": { "custom_model_data": 41 }, "model": "whomine:rename/snow_hat" },
        { "predicate": { "custom_model_data": 42 }, "model": "whomine:rename/swamp_hat" },
        { "predicate": { "custom_model_data": 43 }, "model": "whomine:rename/witch_hat" },
        { "predicate": { "custom_model_data": 44 }, "model": "whomine:rename/santa_hat" },
        { "predicate": { "custom_model_data": 45 }, "model": "whomine:rename/gas_mask" },

        { "predicate": { "custom_model_data": 10000 }, "model": "whomine:decor/acacia_high_padded_armchair" },
        { "predicate": { "custom_model_data": 10001 }, "model": "whomine:decor/acacia_large_table" },
        { "predicate": { "custom_model_data": 10002 }, "model": "whomine:decor/acacia_low_padded_armchair" },
        { "predicate": { "custom_model_data": 10003 }, "model": "whomine:decor/acacia_nightstand" },
        { "predicate": { "custom_model_data": 10004 }, "model": "whomine:decor/acacia_nightstand_0_left" },
        { "predicate": { "custom_model_data": 10005 }, "model": "whomine:decor/acacia_nightstand_0_middle" },
        { "predicate": { "custom_model_data": 10006 }, "model": "whomine:decor/acacia_nightstand_0_right" },
        { "predicate": { "custom_model_data": 10007 }, "model": "whomine:decor/acacia_nightstand_1_left" },
        { "predicate": { "custom_model_data": 10008 }, "model": "whomine:decor/acacia_nightstand_1_middle" },
        { "predicate": { "custom_model_data": 10009 }, "model": "whomine:decor/acacia_nightstand_1_right" },
        { "predicate": { "custom_model_data": 10010 }, "model": "whomine:decor/acacia_padded_chair" },
        { "predicate": { "custom_model_data": 10011 }, "model": "whomine:decor/acacia_padded_rocking_chair" },
        { "predicate": { "custom_model_data": 10012 }, "model": "whomine:decor/acacia_padded_stool" },
        { "predicate": { "custom_model_data": 10013 }, "model": "whomine:decor/acacia_rocking_chair" },
        { "predicate": { "custom_model_data": 10014 }, "model": "whomine:decor/acacia_small_table" },
        { "predicate": { "custom_model_data": 10015 }, "model": "whomine:decor/bamboo_high_padded_armchair" },
        { "predicate": { "custom_model_data": 10016 }, "model": "whomine:decor/bamboo_large_table" },
        { "predicate": { "custom_model_data": 10017 }, "model": "whomine:decor/bamboo_low_padded_armchair" },
        { "predicate": { "custom_model_data": 10018 }, "model": "whomine:decor/bamboo_nightstand" },
        { "predicate": { "custom_model_data": 10019 }, "model": "whomine:decor/bamboo_nightstand_0_left" },
        { "predicate": { "custom_model_data": 10020 }, "model": "whomine:decor/bamboo_nightstand_0_middle" },
        { "predicate": { "custom_model_data": 10021 }, "model": "whomine:decor/bamboo_nightstand_0_right" },
        { "predicate": { "custom_model_data": 10022 }, "model": "whomine:decor/bamboo_nightstand_1_left" },
        { "predicate": { "custom_model_data": 10023 }, "model": "whomine:decor/bamboo_nightstand_1_middle" },
        { "predicate": { "custom_model_data": 10024 }, "model": "whomine:decor/bamboo_nightstand_1_right" },
        { "predicate": { "custom_model_data": 10025 }, "model": "whomine:decor/bamboo_padded_chair" },
        { "predicate": { "custom_model_data": 10026 }, "model": "whomine:decor/bamboo_padded_rocking_chair" },
        { "predicate": { "custom_model_data": 10027 }, "model": "whomine:decor/bamboo_padded_stool" },
        { "predicate": { "custom_model_data": 10028 }, "model": "whomine:decor/bamboo_rocking_chair" },
        { "predicate": { "custom_model_data": 10029 }, "model": "whomine:decor/bamboo_small_table" },
        { "predicate": { "custom_model_data": 10030 }, "model": "whomine:decor/birch_high_padded_armchair" },
        { "predicate": { "custom_model_data": 10031 }, "model": "whomine:decor/birch_large_table" },
        { "predicate": { "custom_model_data": 10032 }, "model": "whomine:decor/birch_low_padded_armchair" },
        { "predicate": { "custom_model_data": 10033 }, "model": "whomine:decor/birch_nightstand" },
        { "predicate": { "custom_model_data": 10034 }, "model": "whomine:decor/birch_nightstand_0_left" },
        { "predicate": { "custom_model_data": 10035 }, "model": "whomine:decor/birch_nightstand_0_middle" },
        { "predicate": { "custom_model_data": 10036 }, "model": "whomine:decor/birch_nightstand_0_right" },
        { "predicate": { "custom_model_data": 10037 }, "model": "whomine:decor/birch_nightstand_1_left" },
        { "predicate": { "custom_model_data": 10038 }, "model": "whomine:decor/birch_nightstand_1_middle" },
        { "predicate": { "custom_model_data": 10039 }, "model": "whomine:decor/birch_nightstand_1_right" },
        { "predicate": { "custom_model_data": 10040 }, "model": "whomine:decor/birch_padded_chair" },
        { "predicate": { "custom_model_data": 10041 }, "model": "whomine:decor/birch_padded_rocking_chair" },
        { "predicate": { "custom_model_data": 10042 }, "model": "whomine:decor/birch_padded_stool" },
        { "predicate": { "custom_model_data": 10043 }, "model": "whomine:decor/birch_rocking_chair" },
        { "predicate": { "custom_model_data": 10044 }, "model": "whomine:decor/birch_small_table" },
        { "predicate": { "custom_model_data": 10045 }, "model": "whomine:decor/cherry_high_padded_armchair" },
        { "predicate": { "custom_model_data": 10046 }, "model": "whomine:decor/cherry_large_table" },
        { "predicate": { "custom_model_data": 10047 }, "model": "whomine:decor/cherry_low_padded_armchair" },
        { "predicate": { "custom_model_data": 10048 }, "model": "whomine:decor/cherry_nightstand" },
        { "predicate": { "custom_model_data": 10049 }, "model": "whomine:decor/cherry_nightstand_0_left" },
        { "predicate": { "custom_model_data": 10050 }, "model": "whomine:decor/cherry_nightstand_0_middle" },
        { "predicate": { "custom_model_data": 10050 }, "model": "whomine:decor/cherry_nightstand_0_right" },
        { "predicate": { "custom_model_data": 10051 }, "model": "whomine:decor/cherry_nightstand_1_left" },
        { "predicate": { "custom_model_data": 10052 }, "model": "whomine:decor/cherry_nightstand_1_middle" },
        { "predicate": { "custom_model_data": 10053 }, "model": "whomine:decor/cherry_nightstand_1_right" },
        { "predicate": { "custom_model_data": 10054 }, "model": "whomine:decor/cherry_padded_chair" },
        { "predicate": { "custom_model_data": 10055 }, "model": "whomine:decor/cherry_padded_rocking_chair" },
        { "predicate": { "custom_model_data": 10056 }, "model": "whomine:decor/cherry_padded_stool" },
        { "predicate": { "custom_model_data": 10057 }, "model": "whomine:decor/cherry_rocking_chair" },
        { "predicate": { "custom_model_data": 10058 }, "model": "whomine:decor/cherry_small_table" },
        { "predicate": { "custom_model_data": 10059 }, "model": "whomine:decor/crimson_high_padded_armchair" },
        { "predicate": { "custom_model_data": 10060 }, "model": "whomine:decor/crimson_large_table" },
        { "predicate": { "custom_model_data": 10061 }, "model": "whomine:decor/crimson_low_padded_armchair" },
        { "predicate": { "custom_model_data": 10062 }, "model": "whomine:decor/crimson_nightstand" },
        { "predicate": { "custom_model_data": 10063 }, "model": "whomine:decor/crimson_nightstand_0_left" },
        { "predicate": { "custom_model_data": 10064 }, "model": "whomine:decor/crimson_nightstand_0_middle" },
        { "predicate": { "custom_model_data": 10065 }, "model": "whomine:decor/crimson_nightstand_0_right" },
        { "predicate": { "custom_model_data": 10066 }, "model": "whomine:decor/crimson_nightstand_1_left" },
        { "predicate": { "custom_model_data": 10067 }, "model": "whomine:decor/crimson_nightstand_1_middle" },
        { "predicate": { "custom_model_data": 10068 }, "model": "whomine:decor/crimson_nightstand_1_right" },
        { "predicate": { "custom_model_data": 10069 }, "model": "whomine:decor/crimson_padded_chair" },
        { "predicate": { "custom_model_data": 10070 }, "model": "whomine:decor/crimson_padded_rocking_chair" },
        { "predicate": { "custom_model_data": 10071 }, "model": "whomine:decor/crimson_padded_stool" },
        { "predicate": { "custom_model_data": 10072 }, "model": "whomine:decor/crimson_rocking_chair" },
        { "predicate": { "custom_model_data": 10073 }, "model": "whomine:decor/crimson_small_table" },
        { "predicate": { "custom_model_data": 10074 }, "model": "whomine:decor/dark_oak_high_padded_armchair" },
        { "predicate": { "custom_model_data": 10075 }, "model": "whomine:decor/dark_oak_large_table" },
        { "predicate": { "custom_model_data": 10076 }, "model": "whomine:decor/dark_oak_low_padded_armchair" },
        { "predicate": { "custom_model_data": 10077 }, "model": "whomine:decor/dark_oak_nightstand" },
        { "predicate": { "custom_model_data": 10078 }, "model": "whomine:decor/dark_oak_nightstand_0_left" },
        { "predicate": { "custom_model_data": 10079 }, "model": "whomine:decor/dark_oak_nightstand_0_middle" },
        { "predicate": { "custom_model_data": 10080 }, "model": "whomine:decor/dark_oak_nightstand_0_right" },
        { "predicate": { "custom_model_data": 10081 }, "model": "whomine:decor/dark_oak_nightstand_1_left" },
        { "predicate": { "custom_model_data": 10082 }, "model": "whomine:decor/dark_oak_nightstand_1_middle" },
        { "predicate": { "custom_model_data": 10083 }, "model": "whomine:decor/dark_oak_nightstand_1_right" },
        { "predicate": { "custom_model_data": 10084 }, "model": "whomine:decor/dark_oak_padded_chair" },
        { "predicate": { "custom_model_data": 10085 }, "model": "whomine:decor/dark_oak_padded_rocking_chair" },
        { "predicate": { "custom_model_data": 10086 }, "model": "whomine:decor/dark_oak_padded_stool" },
        { "predicate": { "custom_model_data": 10087 }, "model": "whomine:decor/dark_oak_rocking_chair" },
        { "predicate": { "custom_model_data": 10088 }, "model": "whomine:decor/dark_oak_small_table" },
        { "predicate": { "custom_model_data": 10089 }, "model": "whomine:decor/jungle_high_padded_armchair" },
        { "predicate": { "custom_model_data": 10090 }, "model": "whomine:decor/jungle_large_table" },
        { "predicate": { "custom_model_data": 10091 }, "model": "whomine:decor/jungle_low_padded_armchair" },
        { "predicate": { "custom_model_data": 10092 }, "model": "whomine:decor/jungle_nightstand" },
        { "predicate": { "custom_model_data": 10093 }, "model": "whomine:decor/jungle_nightstand_0_left" },
        { "predicate": { "custom_model_data": 10094 }, "model": "whomine:decor/jungle_nightstand_0_middle" },
        { "predicate": { "custom_model_data": 10095 }, "model": "whomine:decor/jungle_nightstand_0_right" },
        { "predicate": { "custom_model_data": 10096 }, "model": "whomine:decor/jungle_nightstand_1_left" },
        { "predicate": { "custom_model_data": 10097 }, "model": "whomine:decor/jungle_nightstand_1_middle" },
        { "predicate": { "custom_model_data": 10098 }, "model": "whomine:decor/jungle_nightstand_1_right" },
        { "predicate": { "custom_model_data": 10099 }, "model": "whomine:decor/jungle_padded_chair" },
        { "predicate": { "custom_model_data": 10100 }, "model": "whomine:decor/jungle_padded_rocking_chair" },
        { "predicate": { "custom_model_data": 10101 }, "model": "whomine:decor/jungle_padded_stool" },
        { "predicate": { "custom_model_data": 10102 }, "model": "whomine:decor/jungle_rocking_chair" },
        { "predicate": { "custom_model_data": 10103 }, "model": "whomine:decor/jungle_small_table" },
        { "predicate": { "custom_model_data": 10104 }, "model": "whomine:decor/mangrove_high_padded_armchair" },
        { "predicate": { "custom_model_data": 10105 }, "model": "whomine:decor/mangrove_large_table" },
        { "predicate": { "custom_model_data": 10106 }, "model": "whomine:decor/mangrove_low_padded_armchair" },
        { "predicate": { "custom_model_data": 10107 }, "model": "whomine:decor/mangrove_nightstand" },
        { "predicate": { "custom_model_data": 10108 }, "model": "whomine:decor/mangrove_nightstand_0_left" },
        { "predicate": { "custom_model_data": 10109 }, "model": "whomine:decor/mangrove_nightstand_0_middle" },
        { "predicate": { "custom_model_data": 10110 }, "model": "whomine:decor/mangrove_nightstand_0_right" },
        { "predicate": { "custom_model_data": 10110 }, "model": "whomine:decor/mangrove_nightstand_1_left" },
        { "predicate": { "custom_model_data": 10111 }, "model": "whomine:decor/mangrove_nightstand_1_middle" },
        { "predicate": { "custom_model_data": 10112 }, "model": "whomine:decor/mangrove_nightstand_1_right" },
        { "predicate": { "custom_model_data": 10113 }, "model": "whomine:decor/mangrove_padded_chair" },
        { "predicate": { "custom_model_data": 10114 }, "model": "whomine:decor/mangrove_padded_rocking_chair" },
        { "predicate": { "custom_model_data": 10115 }, "model": "whomine:decor/mangrove_padded_stool" },
        { "predicate": { "custom_model_data": 10116 }, "model": "whomine:decor/mangrove_rocking_chair" },
        { "predicate": { "custom_model_data": 10117 }, "model": "whomine:decor/mangrove_small_table" },
        { "predicate": { "custom_model_data": 10118 }, "model": "whomine:decor/oak_high_padded_armchair" },
        { "predicate": { "custom_model_data": 10119 }, "model": "whomine:decor/oak_large_table" },
        { "predicate": { "custom_model_data": 10120 }, "model": "whomine:decor/oak_low_padded_armchair" },
        { "predicate": { "custom_model_data": 10121 }, "model": "whomine:decor/oak_nightstand" },
        { "predicate": { "custom_model_data": 10122 }, "model": "whomine:decor/oak_nightstand_0_left" },
        { "predicate": { "custom_model_data": 10123 }, "model": "whomine:decor/oak_nightstand_0_middle" },
        { "predicate": { "custom_model_data": 10124 }, "model": "whomine:decor/oak_nightstand_0_right" },
        { "predicate": { "custom_model_data": 10125 }, "model": "whomine:decor/oak_nightstand_1_left" },
        { "predicate": { "custom_model_data": 10126 }, "model": "whomine:decor/oak_nightstand_1_middle" },
        { "predicate": { "custom_model_data": 10127 }, "model": "whomine:decor/oak_nightstand_1_right" },
        { "predicate": { "custom_model_data": 10128 }, "model": "whomine:decor/oak_padded_chair" },
        { "predicate": { "custom_model_data": 10129 }, "model": "whomine:decor/oak_padded_rocking_chair" },
        { "predicate": { "custom_model_data": 10130 }, "model": "whomine:decor/oak_padded_stool" },
        { "predicate": { "custom_model_data": 10131 }, "model": "whomine:decor/oak_rocking_chair" },
        { "predicate": { "custom_model_data": 10132 }, "model": "whomine:decor/oak_small_table" },
        { "predicate": { "custom_model_data": 10133 }, "model": "whomine:decor/spruce_high_padded_armchair" },
        { "predicate": { "custom_model_data": 10134 }, "model": "whomine:decor/spruce_large_table" },
        { "predicate": { "custom_model_data": 10135 }, "model": "whomine:decor/spruce_low_padded_armchair" },
        { "predicate": { "custom_model_data": 10136 }, "model": "whomine:decor/spruce_nightstand" },
        { "predicate": { "custom_model_data": 10137 }, "model": "whomine:decor/spruce_nightstand_0_left" },
        { "predicate": { "custom_model_data": 10138 }, "model": "whomine:decor/spruce_nightstand_0_middle" },
        { "predicate": { "custom_model_data": 10139 }, "model": "whomine:decor/spruce_nightstand_0_right" },
        { "predicate": { "custom_model_data": 10140 }, "model": "whomine:decor/spruce_nightstand_1_left" },
        { "predicate": { "custom_model_data": 10141 }, "model": "whomine:decor/spruce_nightstand_1_middle" },
        { "predicate": { "custom_model_data": 10142 }, "model": "whomine:decor/spruce_nightstand_1_right" },
        { "predicate": { "custom_model_data": 10143 }, "model": "whomine:decor/spruce_padded_chair" },
        { "predicate": { "custom_model_data": 10144 }, "model": "whomine:decor/spruce_padded_rocking_chair" },
        { "predicate": { "custom_model_data": 10145 }, "model": "whomine:decor/spruce_padded_stool" },
        { "predicate": { "custom_model_data": 10146 }, "model": "whomine:decor/spruce_rocking_chair" },
        { "predicate": { "custom_model_data": 10147 }, "model": "whomine:decor/spruce_small_table" },
        { "predicate": { "custom_model_data": 10148 }, "model": "whomine:decor/warped_high_padded_armchair" },
        { "predicate": { "custom_model_data": 10149 }, "model": "whomine:decor/warped_large_table" },
        { "predicate": { "custom_model_data": 10150 }, "model": "whomine:decor/warped_low_padded_armchair" },
        { "predicate": { "custom_model_data": 10151 }, "model": "whomine:decor/warped_nightstand" },
        { "predicate": { "custom_model_data": 10152 }, "model": "whomine:decor/warped_nightstand_0_left" },
        { "predicate": { "custom_model_data": 10153 }, "model": "whomine:decor/warped_nightstand_0_middle" },
        { "predicate": { "custom_model_data": 10154 }, "model": "whomine:decor/warped_nightstand_0_right" },
        { "predicate": { "custom_model_data": 10155 }, "model": "whomine:decor/warped_nightstand_1_left" },
        { "predicate": { "custom_model_data": 10156 }, "model": "whomine:decor/warped_nightstand_1_middle" },
        { "predicate": { "custom_model_data": 10157 }, "model": "whomine:decor/warped_nightstand_1_right" },
        { "predicate": { "custom_model_data": 10158 }, "model": "whomine:decor/warped_padded_chair" },
        { "predicate": { "custom_model_data": 10159 }, "model": "whomine:decor/warped_padded_rocking_chair" },
        { "predicate": { "custom_model_data": 10160 }, "model": "whomine:decor/warped_padded_stool" },
        { "predicate": { "custom_model_data": 10161 }, "model": "whomine:decor/warped_rocking_chair" },
        { "predicate": { "custom_model_data": 10162 }, "model": "whomine:decor/warped_small_table" },
        { "predicate": { "custom_model_data": 10163 }, "model": "whomine:decor/alabastron" },
        { "predicate": { "custom_model_data": 10164 }, "model": "whomine:decor/alabastron_clay" },
        { "predicate": { "custom_model_data": 10165 }, "model": "whomine:decor/alabastron_leaves" },
        { "predicate": { "custom_model_data": 10166 }, "model": "whomine:decor/alabastron_stage_0" },
        { "predicate": { "custom_model_data": 10167 }, "model": "whomine:decor/alabastron_stage_1" },
        { "predicate": { "custom_model_data": 10168 }, "model": "whomine:decor/armchair" },
        { "predicate": { "custom_model_data": 10169 }, "model": "whomine:decor/armchair_left" },
        { "predicate": { "custom_model_data": 10170 }, "model": "whomine:decor/armchair_middle" },
        { "predicate": { "custom_model_data": 10171 }, "model": "whomine:decor/armchair_right" },
        { "predicate": { "custom_model_data": 10172 }, "model": "whomine:decor/bankomat" },
        { "predicate": { "custom_model_data": 10173 }, "model": "whomine:decor/bar_stool" },
        { "predicate": { "custom_model_data": 10174 }, "model": "whomine:decor/bauble" },
        { "predicate": { "custom_model_data": 10175 }, "model": "whomine:decor/bauble_wall" },
        { "predicate": { "custom_model_data": 10176 }, "model": "whomine:decor/bear_plush" },
        { "predicate": { "custom_model_data": 10177 }, "model": "whomine:decor/big_lamp" },
        { "predicate": { "custom_model_data": 10178 }, "model": "whomine:decor/bmo_plush" },
        { "predicate": { "custom_model_data": 10179 }, "model": "whomine:decor/brazier" },
        { "predicate": { "custom_model_data": 10180 }, "model": "whomine:decor/brazier_fired" },
        { "predicate": { "custom_model_data": 10181 }, "model": "whomine:decor/camera" },
        { "predicate": { "custom_model_data": 10182 }, "model": "whomine:decor/cell" },
        { "predicate": { "custom_model_data": 10183 }, "model": "whomine:decor/cell_bee" },
        { "predicate": { "custom_model_data": 10184 }, "model": "whomine:decor/cell_chicken" },
        { "predicate": { "custom_model_data": 10185 }, "model": "whomine:decor/cell_parrot_blue" },
        { "predicate": { "custom_model_data": 10186 }, "model": "whomine:decor/cell_parrot_gray" },
        { "predicate": { "custom_model_data": 10187 }, "model": "whomine:decor/cell_parrot_green" },
        { "predicate": { "custom_model_data": 10188 }, "model": "whomine:decor/cell_parrot_red_blue" },
        { "predicate": { "custom_model_data": 10189 }, "model": "whomine:decor/cell_parrot_yellow_blue" },
        { "predicate": { "custom_model_data": 10190 }, "model": "whomine:decor/cell_slime" },
        { "predicate": { "custom_model_data": 10191 }, "model": "whomine:decor/amethyst_piggy_bank" },
        { "predicate": { "custom_model_data": 10192 }, "model": "whomine:decor/ceramic_piggy_bank" },
        { "predicate": { "custom_model_data": 10193 }, "model": "whomine:decor/coal_piggy_bank" },
        { "predicate": { "custom_model_data": 10194 }, "model": "whomine:decor/copper_piggy_bank" },
        { "predicate": { "custom_model_data": 10195 }, "model": "whomine:decor/oxidized_copper_piggy_bank" },
        { "predicate": { "custom_model_data": 10196 }, "model": "whomine:decor/diamond_piggy_bank" },
        { "predicate": { "custom_model_data": 10197 }, "model": "whomine:decor/emerald_piggy_bank" },
        { "predicate": { "custom_model_data": 10198 }, "model": "whomine:decor/iron_piggy_bank" },
        { "predicate": { "custom_model_data": 10199 }, "model": "whomine:decor/lapis_piggy_bank" },
        { "predicate": { "custom_model_data": 10200 }, "model": "whomine:decor/netherite_piggy_bank" },
        { "predicate": { "custom_model_data": 10201 }, "model": "whomine:decor/plumbum_piggy_bank" },
        { "predicate": { "custom_model_data": 10202 }, "model": "whomine:decor/redstone_piggy_bank" },
        { "predicate": { "custom_model_data": 10203 }, "model": "whomine:decor/cooking_pot" },
        { "predicate": { "custom_model_data": 10204 }, "model": "whomine:decor/cooking_pot_honey_0" },
        { "predicate": { "custom_model_data": 10205 }, "model": "whomine:decor/cooking_pot_honey_1" },
        { "predicate": { "custom_model_data": 10206 }, "model": "whomine:decor/cooking_pot_honey_2" },
        { "predicate": { "custom_model_data": 10207 }, "model": "whomine:decor/cooking_pot_lava_0" },
        { "predicate": { "custom_model_data": 10208 }, "model": "whomine:decor/cooking_pot_lava_1" },
        { "predicate": { "custom_model_data": 10209 }, "model": "whomine:decor/cooking_pot_lava_2" },
        { "predicate": { "custom_model_data": 10210 }, "model": "whomine:decor/cooking_pot_portal_0" },
        { "predicate": { "custom_model_data": 10211 }, "model": "whomine:decor/cooking_pot_portal_1" },
        { "predicate": { "custom_model_data": 10212 }, "model": "whomine:decor/cooking_pot_portal_2" },
        { "predicate": { "custom_model_data": 10213 }, "model": "whomine:decor/cooking_pot_snow_0" },
        { "predicate": { "custom_model_data": 10214 }, "model": "whomine:decor/cooking_pot_snow_1" },
        { "predicate": { "custom_model_data": 10215 }, "model": "whomine:decor/cooking_pot_snow_2" },
        { "predicate": { "custom_model_data": 10216 }, "model": "whomine:decor/cooking_pot_water_0" },
        { "predicate": { "custom_model_data": 10217 }, "model": "whomine:decor/cooking_pot_water_1" },
        { "predicate": { "custom_model_data": 10218 }, "model": "whomine:decor/cooking_pot_water_2" },
        { "predicate": { "custom_model_data": 10219 }, "model": "whomine:decor/deer_head" },
        { "predicate": { "custom_model_data": 10220 }, "model": "whomine:decor/fire_hydrant" },
        { "predicate": { "custom_model_data": 10221 }, "model": "whomine:decor/grate_stand" },
        { "predicate": { "custom_model_data": 10222 }, "model": "whomine:decor/hoglin_head" },
        { "predicate": { "custom_model_data": 10223 }, "model": "whomine:decor/hydria" },
        { "predicate": { "custom_model_data": 10224 }, "model": "whomine:decor/hydria_clay" },
        { "predicate": { "custom_model_data": 10225 }, "model": "whomine:decor/hydria_leaves" },
        { "predicate": { "custom_model_data": 10226 }, "model": "whomine:decor/hydria_stage_0" },
        { "predicate": { "custom_model_data": 10227 }, "model": "whomine:decor/hydria_stage_1" },
        { "predicate": { "custom_model_data": 10228 }, "model": "whomine:decor/icicle_ornament" },
        { "predicate": { "custom_model_data": 10229 }, "model": "whomine:decor/icicle_ornament_wall" },
        { "predicate": { "custom_model_data": 10230 }, "model": "whomine:decor/iron_trashcan" },
        { "predicate": { "custom_model_data": 10231 }, "model": "whomine:decor/large_racoon_plush" },
        { "predicate": { "custom_model_data": 10232 }, "model": "whomine:decor/lebes" },
        { "predicate": { "custom_model_data": 10233 }, "model": "whomine:decor/lebes_clay" },
        { "predicate": { "custom_model_data": 10234 }, "model": "whomine:decor/lebes_leaves" },
        { "predicate": { "custom_model_data": 10235 }, "model": "whomine:decor/lebes_stage_0" },
        { "predicate": { "custom_model_data": 10236 }, "model": "whomine:decor/lebes_stage_1" },
        { "predicate": { "custom_model_data": 10237 }, "model": "whomine:decor/patefon" },
        { "predicate": { "custom_model_data": 10238 }, "model": "whomine:decor/pennant" },
        { "predicate": { "custom_model_data": 10239 }, "model": "whomine:decor/pitcher" },
        { "predicate": { "custom_model_data": 10240 }, "model": "whomine:decor/pitcher_chain" },
        { "predicate": { "custom_model_data": 10241 }, "model": "whomine:decor/pitcher_clay" },
        { "predicate": { "custom_model_data": 10242 }, "model": "whomine:decor/pitcher_clay_chain" },
        { "predicate": { "custom_model_data": 10243 }, "model": "whomine:decor/pitcher_leaves" },
        { "predicate": { "custom_model_data": 10244 }, "model": "whomine:decor/pitcher_leaves_chain" },
        { "predicate": { "custom_model_data": 10245 }, "model": "whomine:decor/pitcher_stage_0" },
        { "predicate": { "custom_model_data": 10246 }, "model": "whomine:decor/pitcher_stage_0_chain" },
        { "predicate": { "custom_model_data": 10247 }, "model": "whomine:decor/pitcher_stage_1" },
        { "predicate": { "custom_model_data": 10248 }, "model": "whomine:decor/pitcher_stage_1_chain" },
        { "predicate": { "custom_model_data": 10249 }, "model": "whomine:decor/poop" },
        { "predicate": { "custom_model_data": 10250 }, "model": "whomine:decor/pouffe" },
        { "predicate": { "custom_model_data": 10251 }, "model": "whomine:decor/santa_socks" },
        { "predicate": { "custom_model_data": 10252 }, "model": "whomine:decor/skeleton_hand" },
        { "predicate": { "custom_model_data": 10253 }, "model": "whomine:decor/skeleton_hand_dirt" },
        { "predicate": { "custom_model_data": 10254 }, "model": "whomine:decor/skeleton_hand_gravel" },
        { "predicate": { "custom_model_data": 10255 }, "model": "whomine:decor/skeleton_hand_stone" },
        { "predicate": { "custom_model_data": 10256 }, "model": "whomine:decor/small_clock" },
        { "predicate": { "custom_model_data": 10257 }, "model": "whomine:decor/small_globe" },
        { "predicate": { "custom_model_data": 10258 }, "model": "whomine:decor/small_lamp" },
        { "predicate": { "custom_model_data": 10259 }, "model": "whomine:decor/snowflake_ball" },
        { "predicate": { "custom_model_data": 10260 }, "model": "whomine:decor/snowflake_ball_wall" },
        { "predicate": { "custom_model_data": 10261 }, "model": "whomine:decor/snowman" },
        { "predicate": { "custom_model_data": 10262 }, "model": "whomine:decor/snowman_ball" },
        { "predicate": { "custom_model_data": 10263 }, "model": "whomine:decor/snowman_ball_wall" },
        { "predicate": { "custom_model_data": 10264 }, "model": "whomine:decor/snowman_broken" },
        { "predicate": { "custom_model_data": 10265 }, "model": "whomine:decor/sonic_cyclops_plush" },
        { "predicate": { "custom_model_data": 10266 }, "model": "whomine:decor/sonic_glitch_plush" },
        { "predicate": { "custom_model_data": 10267 }, "model": "whomine:decor/sonic_plush" },
        { "predicate": { "custom_model_data": 10268 }, "model": "whomine:decor/stamnos" },
        { "predicate": { "custom_model_data": 10269 }, "model": "whomine:decor/stamnos_clay" },
        { "predicate": { "custom_model_data": 10270 }, "model": "whomine:decor/stamnos_leaves" },
        { "predicate": { "custom_model_data": 10271 }, "model": "whomine:decor/stamnos_stage_0" },
        { "predicate": { "custom_model_data": 10272 }, "model": "whomine:decor/stamnos_stage_1" },
        { "predicate": { "custom_model_data": 10273 }, "model": "whomine:decor/star_ball" },
        { "predicate": { "custom_model_data": 10274 }, "model": "whomine:decor/star_ball_wall" },
        { "predicate": { "custom_model_data": 10275 }, "model": "whomine:decor/tree_topper_star" },
        { "predicate": { "custom_model_data": 10276 }, "model": "whomine:decor/wheelbarrow" },
        { "predicate": { "custom_model_data": 10277 }, "model": "whomine:decor/whocintosh" },
        { "predicate": { "custom_model_data": 10278 }, "model": "whomine:decor/whocintosh_mini" },
        { "predicate": { "custom_model_data": 10279 }, "model": "whomine:decor/zoglin_head" },

        { "predicate": { "custom_model_data": 15000 }, "model": "whomine:item/playing_cards/bicycle/blue/card/clovers/a" },
        { "predicate": { "custom_model_data": 15001 }, "model": "whomine:item/playing_cards/bicycle/blue/card/clovers/2" },
        { "predicate": { "custom_model_data": 15002 }, "model": "whomine:item/playing_cards/bicycle/blue/card/clovers/3" },
        { "predicate": { "custom_model_data": 15003 }, "model": "whomine:item/playing_cards/bicycle/blue/card/clovers/4" },
        { "predicate": { "custom_model_data": 15004 }, "model": "whomine:item/playing_cards/bicycle/blue/card/clovers/5" },
        { "predicate": { "custom_model_data": 15005 }, "model": "whomine:item/playing_cards/bicycle/blue/card/clovers/6" },
        { "predicate": { "custom_model_data": 15006 }, "model": "whomine:item/playing_cards/bicycle/blue/card/clovers/7" },
        { "predicate": { "custom_model_data": 15007 }, "model": "whomine:item/playing_cards/bicycle/blue/card/clovers/8" },
        { "predicate": { "custom_model_data": 15008 }, "model": "whomine:item/playing_cards/bicycle/blue/card/clovers/9" },
        { "predicate": { "custom_model_data": 15009 }, "model": "whomine:item/playing_cards/bicycle/blue/card/clovers/10" },
        { "predicate": { "custom_model_data": 15010 }, "model": "whomine:item/playing_cards/bicycle/blue/card/clovers/j" },
        { "predicate": { "custom_model_data": 15011 }, "model": "whomine:item/playing_cards/bicycle/blue/card/clovers/q" },
        { "predicate": { "custom_model_data": 15012 }, "model": "whomine:item/playing_cards/bicycle/blue/card/clovers/k" },
        { "predicate": { "custom_model_data": 15013 }, "model": "whomine:item/playing_cards/bicycle/blue/card/hearts/a" },
        { "predicate": { "custom_model_data": 15014 }, "model": "whomine:item/playing_cards/bicycle/blue/card/hearts/2" },
        { "predicate": { "custom_model_data": 15015 }, "model": "whomine:item/playing_cards/bicycle/blue/card/hearts/3" },
        { "predicate": { "custom_model_data": 15016 }, "model": "whomine:item/playing_cards/bicycle/blue/card/hearts/4" },
        { "predicate": { "custom_model_data": 15017 }, "model": "whomine:item/playing_cards/bicycle/blue/card/hearts/5" },
        { "predicate": { "custom_model_data": 15018 }, "model": "whomine:item/playing_cards/bicycle/blue/card/hearts/6" },
        { "predicate": { "custom_model_data": 15019 }, "model": "whomine:item/playing_cards/bicycle/blue/card/hearts/7" },
        { "predicate": { "custom_model_data": 15020 }, "model": "whomine:item/playing_cards/bicycle/blue/card/hearts/8" },
        { "predicate": { "custom_model_data": 15021 }, "model": "whomine:item/playing_cards/bicycle/blue/card/hearts/9" },
        { "predicate": { "custom_model_data": 15022 }, "model": "whomine:item/playing_cards/bicycle/blue/card/hearts/10" },
        { "predicate": { "custom_model_data": 15023 }, "model": "whomine:item/playing_cards/bicycle/blue/card/hearts/j" },
        { "predicate": { "custom_model_data": 15024 }, "model": "whomine:item/playing_cards/bicycle/blue/card/hearts/q" },
        { "predicate": { "custom_model_data": 15025 }, "model": "whomine:item/playing_cards/bicycle/blue/card/hearts/k" },
        { "predicate": { "custom_model_data": 15026 }, "model": "whomine:item/playing_cards/bicycle/blue/card/pikes/a" },
        { "predicate": { "custom_model_data": 15027 }, "model": "whomine:item/playing_cards/bicycle/blue/card/pikes/2" },
        { "predicate": { "custom_model_data": 15028 }, "model": "whomine:item/playing_cards/bicycle/blue/card/pikes/3" },
        { "predicate": { "custom_model_data": 15029 }, "model": "whomine:item/playing_cards/bicycle/blue/card/pikes/4" },
        { "predicate": { "custom_model_data": 15030 }, "model": "whomine:item/playing_cards/bicycle/blue/card/pikes/5" },
        { "predicate": { "custom_model_data": 15031 }, "model": "whomine:item/playing_cards/bicycle/blue/card/pikes/6" },
        { "predicate": { "custom_model_data": 15032 }, "model": "whomine:item/playing_cards/bicycle/blue/card/pikes/7" },
        { "predicate": { "custom_model_data": 15033 }, "model": "whomine:item/playing_cards/bicycle/blue/card/pikes/8" },
        { "predicate": { "custom_model_data": 15034 }, "model": "whomine:item/playing_cards/bicycle/blue/card/pikes/9" },
        { "predicate": { "custom_model_data": 15035 }, "model": "whomine:item/playing_cards/bicycle/blue/card/pikes/10" },
        { "predicate": { "custom_model_data": 15036 }, "model": "whomine:item/playing_cards/bicycle/blue/card/pikes/j" },
        { "predicate": { "custom_model_data": 15037 }, "model": "whomine:item/playing_cards/bicycle/blue/card/pikes/q" },
        { "predicate": { "custom_model_data": 15038 }, "model": "whomine:item/playing_cards/bicycle/blue/card/pikes/k" },
        { "predicate": { "custom_model_data": 15039 }, "model": "whomine:item/playing_cards/bicycle/blue/card/tiles/a" },
        { "predicate": { "custom_model_data": 15040 }, "model": "whomine:item/playing_cards/bicycle/blue/card/tiles/2" },
        { "predicate": { "custom_model_data": 15041 }, "model": "whomine:item/playing_cards/bicycle/blue/card/tiles/3" },
        { "predicate": { "custom_model_data": 15042 }, "model": "whomine:item/playing_cards/bicycle/blue/card/tiles/4" },
        { "predicate": { "custom_model_data": 15043 }, "model": "whomine:item/playing_cards/bicycle/blue/card/tiles/5" },
        { "predicate": { "custom_model_data": 15044 }, "model": "whomine:item/playing_cards/bicycle/blue/card/tiles/6" },
        { "predicate": { "custom_model_data": 15045 }, "model": "whomine:item/playing_cards/bicycle/blue/card/tiles/7" },
        { "predicate": { "custom_model_data": 15046 }, "model": "whomine:item/playing_cards/bicycle/blue/card/tiles/8" },
        { "predicate": { "custom_model_data": 15047 }, "model": "whomine:item/playing_cards/bicycle/blue/card/tiles/9" },
        { "predicate": { "custom_model_data": 15048 }, "model": "whomine:item/playing_cards/bicycle/blue/card/tiles/10" },
        { "predicate": { "custom_model_data": 15049 }, "model": "whomine:item/playing_cards/bicycle/blue/card/tiles/j" },
        { "predicate": { "custom_model_data": 15050 }, "model": "whomine:item/playing_cards/bicycle/blue/card/tiles/q" },
        { "predicate": { "custom_model_data": 15051 }, "model": "whomine:item/playing_cards/bicycle/blue/card/tiles/k" },
        { "predicate": { "custom_model_data": 15052 }, "model": "whomine:item/playing_cards/bicycle/blue/card/joker/black" },
        { "predicate": { "custom_model_data": 15053 }, "model": "whomine:item/playing_cards/bicycle/blue/card/joker/red" },
        { "predicate": { "custom_model_data": 15054 }, "model": "whomine:item/playing_cards/bicycle/red/card/clovers/a" },
        { "predicate": { "custom_model_data": 15055 }, "model": "whomine:item/playing_cards/bicycle/red/card/clovers/2" },
        { "predicate": { "custom_model_data": 15056 }, "model": "whomine:item/playing_cards/bicycle/red/card/clovers/3" },
        { "predicate": { "custom_model_data": 15058 }, "model": "whomine:item/playing_cards/bicycle/red/card/clovers/4" },
        { "predicate": { "custom_model_data": 15059 }, "model": "whomine:item/playing_cards/bicycle/red/card/clovers/5" },
        { "predicate": { "custom_model_data": 15060 }, "model": "whomine:item/playing_cards/bicycle/red/card/clovers/6" },
        { "predicate": { "custom_model_data": 15061 }, "model": "whomine:item/playing_cards/bicycle/red/card/clovers/7" },
        { "predicate": { "custom_model_data": 15062 }, "model": "whomine:item/playing_cards/bicycle/red/card/clovers/8" },
        { "predicate": { "custom_model_data": 15063 }, "model": "whomine:item/playing_cards/bicycle/red/card/clovers/9" },
        { "predicate": { "custom_model_data": 15064 }, "model": "whomine:item/playing_cards/bicycle/red/card/clovers/10" },
        { "predicate": { "custom_model_data": 15065 }, "model": "whomine:item/playing_cards/bicycle/red/card/clovers/j" },
        { "predicate": { "custom_model_data": 15066 }, "model": "whomine:item/playing_cards/bicycle/red/card/clovers/q" },
        { "predicate": { "custom_model_data": 15067 }, "model": "whomine:item/playing_cards/bicycle/red/card/clovers/k" },
        { "predicate": { "custom_model_data": 15068 }, "model": "whomine:item/playing_cards/bicycle/red/card/hearts/a" },
        { "predicate": { "custom_model_data": 15079 }, "model": "whomine:item/playing_cards/bicycle/red/card/hearts/2" },
        { "predicate": { "custom_model_data": 15070 }, "model": "whomine:item/playing_cards/bicycle/red/card/hearts/3" },
        { "predicate": { "custom_model_data": 15071 }, "model": "whomine:item/playing_cards/bicycle/red/card/hearts/4" },
        { "predicate": { "custom_model_data": 15072 }, "model": "whomine:item/playing_cards/bicycle/red/card/hearts/5" },
        { "predicate": { "custom_model_data": 15073 }, "model": "whomine:item/playing_cards/bicycle/red/card/hearts/6" },
        { "predicate": { "custom_model_data": 15074 }, "model": "whomine:item/playing_cards/bicycle/red/card/hearts/7" },
        { "predicate": { "custom_model_data": 15075 }, "model": "whomine:item/playing_cards/bicycle/red/card/hearts/8" },
        { "predicate": { "custom_model_data": 15076 }, "model": "whomine:item/playing_cards/bicycle/red/card/hearts/9" },
        { "predicate": { "custom_model_data": 15077 }, "model": "whomine:item/playing_cards/bicycle/red/card/hearts/10" },
        { "predicate": { "custom_model_data": 15078 }, "model": "whomine:item/playing_cards/bicycle/red/card/hearts/j" },
        { "predicate": { "custom_model_data": 15079 }, "model": "whomine:item/playing_cards/bicycle/red/card/hearts/q" },
        { "predicate": { "custom_model_data": 15080 }, "model": "whomine:item/playing_cards/bicycle/red/card/hearts/k" },
        { "predicate": { "custom_model_data": 15081 }, "model": "whomine:item/playing_cards/bicycle/red/card/pikes/a" },
        { "predicate": { "custom_model_data": 15082 }, "model": "whomine:item/playing_cards/bicycle/red/card/pikes/2" },
        { "predicate": { "custom_model_data": 15083 }, "model": "whomine:item/playing_cards/bicycle/red/card/pikes/3" },
        { "predicate": { "custom_model_data": 15084 }, "model": "whomine:item/playing_cards/bicycle/red/card/pikes/4" },
        { "predicate": { "custom_model_data": 15085 }, "model": "whomine:item/playing_cards/bicycle/red/card/pikes/5" },
        { "predicate": { "custom_model_data": 15086 }, "model": "whomine:item/playing_cards/bicycle/red/card/pikes/6" },
        { "predicate": { "custom_model_data": 15087 }, "model": "whomine:item/playing_cards/bicycle/red/card/pikes/7" },
        { "predicate": { "custom_model_data": 15088 }, "model": "whomine:item/playing_cards/bicycle/red/card/pikes/8" },
        { "predicate": { "custom_model_data": 15089 }, "model": "whomine:item/playing_cards/bicycle/red/card/pikes/9" },
        { "predicate": { "custom_model_data": 15090 }, "model": "whomine:item/playing_cards/bicycle/red/card/pikes/10" },
        { "predicate": { "custom_model_data": 15091 }, "model": "whomine:item/playing_cards/bicycle/red/card/pikes/j" },
        { "predicate": { "custom_model_data": 15092 }, "model": "whomine:item/playing_cards/bicycle/red/card/pikes/q" },
        { "predicate": { "custom_model_data": 15093 }, "model": "whomine:item/playing_cards/bicycle/red/card/pikes/k" },
        { "predicate": { "custom_model_data": 15094 }, "model": "whomine:item/playing_cards/bicycle/red/card/tiles/a" },
        { "predicate": { "custom_model_data": 15095 }, "model": "whomine:item/playing_cards/bicycle/red/card/tiles/2" },
        { "predicate": { "custom_model_data": 15096 }, "model": "whomine:item/playing_cards/bicycle/red/card/tiles/3" },
        { "predicate": { "custom_model_data": 15097 }, "model": "whomine:item/playing_cards/bicycle/red/card/tiles/4" },
        { "predicate": { "custom_model_data": 15098 }, "model": "whomine:item/playing_cards/bicycle/red/card/tiles/5" },
        { "predicate": { "custom_model_data": 15099 }, "model": "whomine:item/playing_cards/bicycle/red/card/tiles/6" },
        { "predicate": { "custom_model_data": 15100 }, "model": "whomine:item/playing_cards/bicycle/red/card/tiles/7" },
        { "predicate": { "custom_model_data": 15101 }, "model": "whomine:item/playing_cards/bicycle/red/card/tiles/8" },
        { "predicate": { "custom_model_data": 15102 }, "model": "whomine:item/playing_cards/bicycle/red/card/tiles/9" },
        { "predicate": { "custom_model_data": 15103 }, "model": "whomine:item/playing_cards/bicycle/red/card/tiles/10" },
        { "predicate": { "custom_model_data": 15104 }, "model": "whomine:item/playing_cards/bicycle/red/card/tiles/j" },
        { "predicate": { "custom_model_data": 15105 }, "model": "whomine:item/playing_cards/bicycle/red/card/tiles/q" },
        { "predicate": { "custom_model_data": 15106 }, "model": "whomine:item/playing_cards/bicycle/red/card/tiles/k" },
        { "predicate": { "custom_model_data": 15107 }, "model": "whomine:item/playing_cards/bicycle/red/card/joker/black" },
        { "predicate": { "custom_model_data": 15108 }, "model": "whomine:item/playing_cards/bicycle/red/card/joker/red" },
        { "predicate": { "custom_model_data": 15109 }, "model": "whomine:item/dosimeter" },
        { "predicate": { "custom_model_data": 15110 }, "model": "whomine:item/dosimeter_fine" },
        { "predicate": { "custom_model_data": 15111 }, "model": "whomine:item/dosimeter_warning" },
        { "predicate": { "custom_model_data": 15112 }, "model": "whomine:item/dosimeter_severe" },
        { "predicate": { "custom_model_data": 15113 }, "model": "whomine:item/leather_hat" },
        { "predicate": { "custom_model_data": 15114 }, "model": "whomine:item/magnifier" }
    ]
}
