{
	"credit": "Made by Poloskun_ http://www.youtube.com/c/Enchig",
	"texture_size": [32, 32],
	"textures": {
		"0": "./glaive",
		"particle": "./glaive"
	},
	"gui_light": "front",
	"elements": [
		{
			"from": [15, 0, 0],
			"to": [16, 1, 1],
			"faces": {
				"north": {"uv": [0, 14.5, 0.5, 15], "texture": "#0"},
				"east": {"uv": [0, 14.5, 0.5, 15], "texture": "#0"},
				"south": {"uv": [0, 14.5, 0.5, 15], "texture": "#0"},
				"west": {"uv": [0, 14.5, 0.5, 15], "texture": "#0"},
				"up": {"uv": [0, 14.5, 0.5, 15], "texture": "#0"},
				"down": {"uv": [0, 14.5, 0.5, 15], "texture": "#0"}
			}
		},
		{
			"from": [-14, 30, 0],
			"to": [-13, 31, 1],
			"faces": {
				"north": {"uv": [13.9995, 0, 14.4995, 0.5], "texture": "#0"},
				"east": {"uv": [13.9995, 0, 14.4995, 0.5], "texture": "#0"},
				"south": {"uv": [13.9995, 0, 14.4995, 0.5], "texture": "#0"},
				"west": {"uv": [13.9995, 0, 14.4995, 0.5], "texture": "#0"},
				"up": {"uv": [13.9995, 0, 14.4995, 0.5], "texture": "#0"},
				"down": {"uv": [13.9995, 0, 14.4995, 0.5], "texture": "#0"}
			}
		},
		{
			"from": [13, 1, 0],
			"to": [15, 3, 1],
			"faces": {
				"north": {"uv": [0.5, 13.5, 1.4995, 14.4995], "texture": "#0"},
				"east": {"uv": [0.5, 13.5, 1, 14.4995], "texture": "#0"},
				"south": {"uv": [0.5, 13.5, 1.4995, 14.4995], "rotation": 90, "texture": "#0"},
				"west": {"uv": [1, 13.5, 1.4995, 14.4995], "texture": "#0"},
				"up": {"uv": [0.5, 13.5, 1.4995, 13.9995], "rotation": 180, "texture": "#0"},
				"down": {"uv": [0.5, 13.9995, 1.4995, 14.4995], "rotation": 180, "texture": "#0"}
			}
		},
		{
			"from": [12, 2, 0],
			"to": [13, 4, 1],
			"faces": {
				"north": {"uv": [1.5, 13, 2, 13.9995], "texture": "#0"},
				"east": {"uv": [1.5, 13, 2, 13.9995], "texture": "#0"},
				"south": {"uv": [1.5, 13, 2, 13.9995], "texture": "#0"},
				"west": {"uv": [1.5, 13, 2, 13.9995], "texture": "#0"},
				"up": {"uv": [1.5, 13, 2, 13.5], "texture": "#0"},
				"down": {"uv": [1.5, 13.5, 2, 13.9995], "texture": "#0"}
			}
		},
		{
			"from": [11, 3, 0],
			"to": [12, 5, 1],
			"faces": {
				"north": {"uv": [2, 12.5, 2.5, 13.499], "texture": "#0"},
				"east": {"uv": [2, 12.5, 2.5, 13.499], "texture": "#0"},
				"south": {"uv": [2, 12.5, 2.5, 13.499], "texture": "#0"},
				"west": {"uv": [2, 12.5, 2.5, 13.499], "texture": "#0"},
				"up": {"uv": [2, 12.5, 2.5, 12.9995], "texture": "#0"},
				"down": {"uv": [2, 13, 2.5, 13.4995], "texture": "#0"}
			}
		},
		{
			"from": [10, 4, 0],
			"to": [11, 6, 1],
			"faces": {
				"north": {"uv": [2.5, 12, 2.9995, 12.9985], "texture": "#0"},
				"east": {"uv": [2.5, 12, 2.9995, 12.9985], "texture": "#0"},
				"south": {"uv": [2.5, 12, 2.9995, 12.9985], "texture": "#0"},
				"west": {"uv": [2.5, 12, 2.9995, 12.9985], "texture": "#0"},
				"up": {"uv": [2.5, 12, 2.9995, 12.4995], "texture": "#0"},
				"down": {"uv": [2.5, 12.5, 2.9995, 12.999], "texture": "#0"}
			}
		},
		{
			"from": [9, 5, 0],
			"to": [10, 7, 1],
			"faces": {
				"north": {"uv": [3, 11.5, 3.4995, 12.4985], "texture": "#0"},
				"east": {"uv": [3, 11.5, 3.4995, 12.4985], "texture": "#0"},
				"south": {"uv": [3, 11.5, 3.4995, 12.4985], "texture": "#0"},
				"west": {"uv": [3, 11.5, 3.4995, 12.4985], "texture": "#0"},
				"up": {"uv": [3, 11.5, 3.4995, 11.9995], "texture": "#0"},
				"down": {"uv": [3, 12, 3.4995, 12.499], "texture": "#0"}
			}
		},
		{
			"from": [8, 6, 0],
			"to": [9, 8, 1],
			"faces": {
				"north": {"uv": [3.5, 11, 3.9995, 11.998], "texture": "#0"},
				"east": {"uv": [3.5, 11, 3.9995, 11.998], "texture": "#0"},
				"south": {"uv": [3.5, 11, 3.9995, 11.998], "texture": "#0"},
				"west": {"uv": [3.5, 11, 3.9995, 11.998], "texture": "#0"},
				"up": {"uv": [3.5, 11, 3.9995, 11.499], "texture": "#0"},
				"down": {"uv": [3.5, 11.5, 3.9995, 11.999], "texture": "#0"}
			}
		},
		{
			"from": [7, 7, 0],
			"to": [8, 9, 1],
			"faces": {
				"north": {"uv": [4, 10.5, 4.499, 11.498], "texture": "#0"},
				"east": {"uv": [4, 10.5, 4.499, 11.498], "texture": "#0"},
				"south": {"uv": [4, 10.5, 4.499, 11.498], "texture": "#0"},
				"west": {"uv": [4, 10.5, 4.499, 11.498], "texture": "#0"},
				"up": {"uv": [4, 10.5, 4.499, 10.999], "texture": "#0"},
				"down": {"uv": [4, 11, 4.499, 11.499], "texture": "#0"}
			}
		},
		{
			"from": [6, 8, 0],
			"to": [7, 10, 1],
			"faces": {
				"north": {"uv": [4.5, 10, 4.999, 10.998], "texture": "#0"},
				"east": {"uv": [4.5, 10, 4.999, 10.998], "texture": "#0"},
				"south": {"uv": [4.5, 10, 4.999, 10.998], "texture": "#0"},
				"west": {"uv": [4.5, 10, 4.999, 10.998], "texture": "#0"},
				"up": {"uv": [4.5, 10, 4.999, 10.499], "texture": "#0"},
				"down": {"uv": [4.5, 10.5, 4.999, 10.999], "texture": "#0"}
			}
		},
		{
			"from": [5, 9, 0],
			"to": [6, 11, 1],
			"faces": {
				"north": {"uv": [5, 9.5, 5.499, 10.498], "texture": "#0"},
				"east": {"uv": [5, 9.5, 5.499, 10.498], "texture": "#0"},
				"south": {"uv": [5, 9.5, 5.499, 10.498], "texture": "#0"},
				"west": {"uv": [5, 9.5, 5.499, 10.498], "texture": "#0"},
				"up": {"uv": [5, 9.5, 5.499, 9.999], "texture": "#0"},
				"down": {"uv": [5, 10, 5.499, 10.499], "texture": "#0"}
			}
		},
		{
			"from": [4, 10, 0],
			"to": [5, 12, 1],
			"faces": {
				"north": {"uv": [5.5, 9, 5.9985, 9.998], "texture": "#0"},
				"east": {"uv": [5.5, 9, 5.9985, 9.998], "texture": "#0"},
				"south": {"uv": [5.5, 9, 5.9985, 9.998], "texture": "#0"},
				"west": {"uv": [5.5, 9, 5.9985, 9.998], "texture": "#0"},
				"up": {"uv": [5.5, 9, 5.9985, 9.499], "texture": "#0"},
				"down": {"uv": [5.5, 9.5, 5.9985, 9.999], "texture": "#0"}
			}
		},
		{
			"from": [3, 11, 0],
			"to": [4, 13, 1],
			"faces": {
				"north": {"uv": [6, 8.5, 6.498, 9.498], "texture": "#0"},
				"east": {"uv": [6, 8.5, 6.498, 9.498], "texture": "#0"},
				"south": {"uv": [6, 8.5, 6.498, 9.498], "texture": "#0"},
				"west": {"uv": [6, 8.5, 6.498, 9.498], "texture": "#0"},
				"up": {"uv": [6, 8.5, 6.498, 8.999], "texture": "#0"},
				"down": {"uv": [6, 9, 6.498, 9.499], "texture": "#0"}
			}
		},
		{
			"from": [2, 12, 0],
			"to": [3, 14, 1],
			"faces": {
				"north": {"uv": [6.5, 8, 6.9975, 8.998], "texture": "#0"},
				"east": {"uv": [6.5, 8, 6.9975, 8.998], "texture": "#0"},
				"south": {"uv": [6.5, 8, 6.9975, 8.998], "texture": "#0"},
				"west": {"uv": [6.5, 8, 6.9975, 8.998], "texture": "#0"},
				"up": {"uv": [6.5, 8, 6.9975, 8.499], "texture": "#0"},
				"down": {"uv": [6.5, 8.5, 6.997, 8.999], "texture": "#0"}
			}
		},
		{
			"from": [1, 13, 0],
			"to": [2, 15, 1],
			"faces": {
				"north": {"uv": [6.9995, 7.5, 7.497, 8.498], "texture": "#0"},
				"east": {"uv": [6.9995, 7.5, 7.497, 8.498], "texture": "#0"},
				"south": {"uv": [6.9995, 7.5, 7.497, 8.498], "texture": "#0"},
				"west": {"uv": [6.9995, 7.5, 7.497, 8.498], "texture": "#0"},
				"up": {"uv": [6.9995, 7.5, 7.497, 7.999], "texture": "#0"},
				"down": {"uv": [6.9995, 8, 7.4965, 8.499], "texture": "#0"}
			}
		},
		{
			"from": [0, 14, 0],
			"to": [1, 16, 1],
			"faces": {
				"north": {"uv": [7.5, 6.9995, 7.997, 7.9975], "texture": "#0"},
				"east": {"uv": [7.5, 6.9995, 7.997, 7.9975], "texture": "#0"},
				"south": {"uv": [7.5, 6.9995, 7.997, 7.9975], "texture": "#0"},
				"west": {"uv": [7.5, 6.9995, 7.997, 7.9975], "texture": "#0"},
				"up": {"uv": [7.5, 6.9995, 7.997, 7.4985], "texture": "#0"},
				"down": {"uv": [7.5, 7.5, 7.997, 7.999], "texture": "#0"}
			}
		},
		{
			"from": [-1, 15, 0],
			"to": [0, 17, 1],
			"faces": {
				"north": {"uv": [8, 6.5, 8.4965, 7.498], "texture": "#0"},
				"east": {"uv": [8, 6.5, 8.4965, 7.498], "texture": "#0"},
				"south": {"uv": [8, 6.5, 8.4965, 7.498], "texture": "#0"},
				"west": {"uv": [8, 6.5, 8.4965, 7.498], "texture": "#0"},
				"up": {"uv": [8, 6.5, 8.4965, 6.999], "texture": "#0"},
				"down": {"uv": [8, 6.9995, 8.4965, 7.4985], "texture": "#0"}
			}
		},
		{
			"from": [-2, 16, 0],
			"to": [-1, 18, 1],
			"faces": {
				"north": {"uv": [8.5, 6, 8.9965, 6.998], "texture": "#0"},
				"east": {"uv": [8.5, 6, 8.9965, 6.998], "texture": "#0"},
				"south": {"uv": [8.5, 6, 8.9965, 6.998], "texture": "#0"},
				"west": {"uv": [8.5, 6, 8.9965, 6.998], "texture": "#0"},
				"up": {"uv": [8.5, 6, 8.9965, 6.499], "texture": "#0"},
				"down": {"uv": [8.5, 6.5, 8.9965, 6.999], "texture": "#0"}
			}
		},
		{
			"from": [-4, 17, 0],
			"to": [-2, 20, 1],
			"faces": {
				"north": {"uv": [9, 5, 9.9995, 6.5], "texture": "#0"},
				"east": {"uv": [9, 5, 9.5, 6.5], "texture": "#0"},
				"south": {"uv": [9.9995, 5, 9, 6.5], "texture": "#0"},
				"west": {"uv": [9.5, 5, 9.9995, 6.5], "texture": "#0"},
				"up": {"uv": [9, 5, 9.9995, 5.5], "rotation": 180, "texture": "#0"},
				"down": {"uv": [9, 6, 9.9995, 6.5], "rotation": 180, "texture": "#0"}
			}
		},
		{
			"from": [-5, 18, 0],
			"to": [-3, 21, 1],
			"faces": {
				"north": {"uv": [9.5, 4.5, 10.499, 6], "texture": "#0"},
				"east": {"uv": [9.5, 4.5, 9.9995, 6], "texture": "#0"},
				"south": {"uv": [10.499, 4.5, 9.5, 6], "texture": "#0"},
				"west": {"uv": [10, 4.5, 10.4995, 6], "texture": "#0"},
				"up": {"uv": [9.5, 4.5, 10.499, 5], "rotation": 180, "texture": "#0"},
				"down": {"uv": [9.5, 5.5, 10.499, 5.9995], "rotation": 180, "texture": "#0"}
			}
		},
		{
			"from": [-6, 19, 0],
			"to": [-4, 22, 1],
			"faces": {
				"north": {"uv": [10, 4, 10.999, 5.5], "texture": "#0"},
				"east": {"uv": [10, 4, 10.4995, 5.5], "texture": "#0"},
				"south": {"uv": [10.999, 4, 10, 5.5], "texture": "#0"},
				"west": {"uv": [10.5, 4, 10.9995, 5.5], "texture": "#0"},
				"up": {"uv": [10, 4, 10.999, 4.4995], "rotation": 180, "texture": "#0"},
				"down": {"uv": [10, 5, 10.999, 5.4995], "rotation": 180, "texture": "#0"}
			}
		},
		{
			"from": [-7, 20, 0],
			"to": [-5, 23, 1],
			"faces": {
				"north": {"uv": [10, 4, 10.999, 5.5], "texture": "#0"},
				"east": {"uv": [10, 4, 10.4995, 5.5], "texture": "#0"},
				"south": {"uv": [10.999, 4, 10, 5.5], "texture": "#0"},
				"west": {"uv": [10.5, 4, 10.9995, 5.5], "texture": "#0"},
				"up": {"uv": [10, 4, 10.999, 4.4995], "rotation": 180, "texture": "#0"},
				"down": {"uv": [10, 5, 10.999, 5.4995], "rotation": 180, "texture": "#0"}
			}
		},
		{
			"from": [-8, 21, 0],
			"to": [-6, 24, 1],
			"faces": {
				"north": {"uv": [10.5, 3.5, 11.499, 5], "texture": "#0"},
				"east": {"uv": [10.5, 3.5, 10.9995, 5], "texture": "#0"},
				"south": {"uv": [11.499, 3.5, 10.5, 5], "texture": "#0"},
				"west": {"uv": [11, 3.5, 11.499, 5], "texture": "#0"},
				"up": {"uv": [10.5, 3.5, 11.499, 3.9995], "rotation": 180, "texture": "#0"},
				"down": {"uv": [10.5, 4.5, 11.499, 4.9995], "rotation": 180, "texture": "#0"}
			}
		},
		{
			"from": [-9, 22, 0],
			"to": [-7, 25, 1],
			"faces": {
				"north": {"uv": [11, 3, 11.9985, 4.5], "texture": "#0"},
				"east": {"uv": [11, 3, 11.499, 4.5], "texture": "#0"},
				"south": {"uv": [11.9985, 3, 11, 4.5], "texture": "#0"},
				"west": {"uv": [11.5, 3, 11.999, 4.5], "texture": "#0"},
				"up": {"uv": [11, 3, 11.9985, 3.4995], "rotation": 180, "texture": "#0"},
				"down": {"uv": [11, 4, 11.9985, 4.499], "rotation": 180, "texture": "#0"}
			}
		},
		{
			"from": [-10, 23, 0],
			"to": [-8, 26, 1],
			"faces": {
				"north": {"uv": [11.5, 2.5, 12.4985, 4], "texture": "#0"},
				"east": {"uv": [11.5, 2.5, 11.999, 4], "texture": "#0"},
				"south": {"uv": [12.4985, 2.5, 11.5, 4], "texture": "#0"},
				"west": {"uv": [12, 2.5, 12.499, 4], "texture": "#0"},
				"up": {"uv": [11.5, 2.5, 12.4985, 2.999], "rotation": 180, "texture": "#0"},
				"down": {"uv": [11.5, 3.5, 12.4985, 3.999], "rotation": 180, "texture": "#0"}
			}
		},
		{
			"from": [-11, 24, 0],
			"to": [-9, 27, 1],
			"faces": {
				"north": {"uv": [12, 2, 12.9985, 3.5], "texture": "#0"},
				"east": {"uv": [12, 2, 12.499, 3.5], "texture": "#0"},
				"south": {"uv": [12.9985, 2, 12, 3.5], "texture": "#0"},
				"west": {"uv": [12.5, 2, 12.9985, 3.5], "texture": "#0"},
				"up": {"uv": [12, 2, 12.9985, 2.499], "rotation": 180, "texture": "#0"},
				"down": {"uv": [12, 3, 12.9985, 3.499], "rotation": 180, "texture": "#0"}
			}
		},
		{
			"from": [-12, 25, 0],
			"to": [-10, 28, 1],
			"faces": {
				"north": {"uv": [12.5, 1.5, 13.498, 3], "texture": "#0"},
				"east": {"uv": [12.5, 1.5, 12.9985, 3], "texture": "#0"},
				"south": {"uv": [13.498, 1.5, 12.5, 3], "texture": "#0"},
				"west": {"uv": [13, 1.5, 13.498, 3], "texture": "#0"},
				"up": {"uv": [12.5, 1.5, 13.498, 1.999], "rotation": 180, "texture": "#0"},
				"down": {"uv": [12.5, 2.5, 13.498, 2.999], "rotation": 180, "texture": "#0"}
			}
		},
		{
			"from": [-13, 26, 0],
			"to": [-11, 29, 1],
			"faces": {
				"north": {"uv": [13, 1, 13.998, 2.5], "texture": "#0"},
				"east": {"uv": [13, 1, 13.498, 2.5], "texture": "#0"},
				"south": {"uv": [13.998, 1, 13, 2.5], "texture": "#0"},
				"west": {"uv": [13.5, 1, 13.9975, 2.5], "texture": "#0"},
				"up": {"uv": [13, 1, 13.998, 1.499], "rotation": 180, "texture": "#0"},
				"down": {"uv": [13, 2, 13.998, 2.499], "rotation": 180, "texture": "#0"}
			}
		},
		{
			"from": [-14, 27, 0],
			"to": [-12, 30, 1],
			"faces": {
				"north": {"uv": [13.5, 0.5, 14.498, 2], "texture": "#0"},
				"east": {"uv": [13.5, 0.5, 13.9975, 2], "texture": "#0"},
				"south": {"uv": [14.498, 0.5, 13.5, 2], "texture": "#0"},
				"west": {"uv": [13.9995, 0.5, 14.497, 2], "texture": "#0"},
				"up": {"uv": [13.5, 0.5, 14.498, 0.999], "rotation": 180, "texture": "#0"},
				"down": {"uv": [13.5, 1.5, 14.498, 1.999], "rotation": 180, "texture": "#0"}
			}
		},
		{
			"from": [-5, 16, 0],
			"to": [-3, 17, 1],
			"faces": {
				"north": {"uv": [9.5, 6.5, 10.4995, 6.9995], "texture": "#0"},
				"east": {"uv": [9.5, 6.5, 9.9995, 6.9995], "texture": "#0"},
				"south": {"uv": [9.5, 6.5, 10.4995, 6.9995], "rotation": 180, "texture": "#0"},
				"west": {"uv": [10, 6.5, 10.5, 6.9995], "texture": "#0"},
				"up": {"uv": [9.5, 6.5, 10.4995, 6.9995], "rotation": 180, "texture": "#0"},
				"down": {"uv": [9.5, 6.5, 10.4995, 6.9995], "rotation": 180, "texture": "#0"}
			}
		}
	],
	"display": {
		"thirdperson_righthand": {
			"rotation": [50, -90, 0],
			"translation": [-7.75, -1.75, 1.5]
		},
		"thirdperson_lefthand": {
			"rotation": [126, 90, 0],
			"translation": [7.25, -2.5, -1.75]
		},
		"firstperson_righthand": {
			"rotation": [4, -90, 0],
			"translation": [-2, 0, 0]
		},
		"firstperson_lefthand": {
			"rotation": [4, 90, 0],
			"translation": [13, 0, 0]
		},
		"ground": {
			"rotation": [90, 0, 0],
			"translation": [7, -10.5, -6.75]
		},
		"gui": {
			"translation": [4.5, -4.5, 0],
			"scale": [0.88, 0.88, 0.88]
		},
		"fixed": {
			"translation": [4.75, -5, 12],
			"scale": [1.69, 1.69, 1.69]
		}
	}
}